{
  "homepage": "https://www.curseforge.com/minecraft/mc-mods/vanillatweaks",
  "promos": {
    "1.17.1-latest": "1.17.1-1.5.48",
    "1.18-latest": "1.5.52",
    "1.18-recommended": "1.5.52",
    "1.18.1-latest": "1.5.52",
    "1.18.1-recommended": "1.5.53",
    "1.18.2-recommended": "1.5.57",
    "1.19-recommended": "1.5.61"
  },
  "1.18": {
    "1.18-1.5.50": "Updated to Minecraft 1.18",
    "1.5.51": "Fixed pedestal not saving data.\n Made Lava pocket disabler work again",
    "1.5.52": "Added back JEI support.\n Made lava pocket disabler also disable open lava pockets.",
    "1.5.53": "Ported the whole mod MultiLoader which means same time update as Forge versions.\n Fixed issue with pedestal not displaying items on world reload.",
    "1.5.57": "Fixed crash with null entity due to debug log"
  },
  "1.19": {
    "1.5.61": "Fix compatability with forge 41.0.79"
  }
}